dlview/__init__.py
dlview/dlview.py
dlview-0.1.1.dist-info/METADATA
dlview-0.1.1.dist-info/WHEEL
dlview-0.1.1.dist-info/top_level.txt
dlview-0.1.1.dist-info/RECORD
