Metadata-Version: 2.1
Name: dlview
Version: 0.1.1
Summary: A data print helper for deep learning projects
Home-page: 
Author: Lihao Wang
Author-email: lihaowang@yahoo.com
License: UNKNOWN
Platform: UNKNOWN
Classifier: Programming Language :: Python :: 3
Classifier: License :: OSI Approved :: MIT License
Classifier: Operating System :: OS Independent
Requires-Python: >=3.7
